PG365/__init__.py
PG365/example.py
pg365-1.0.1.dist-info/LICENSE
pg365-1.0.1.dist-info/METADATA
pg365-1.0.1.dist-info/WHEEL
pg365-1.0.1.dist-info/top_level.txt
pg365-1.0.1.dist-info/RECORD
