Metadata-Version: 2.1
Name: pg365
Version: 1.0.1
Summary: PG365 ปลอดภัย มั่นคง สล็อต365 pg365slot
Author-email: pg365 <pg365@example.com>
Project-URL: Homepage, https://github.com/
Classifier: Programming Language :: Python :: 3
Classifier: License :: OSI Approved :: MIT License
Classifier: Operating System :: OS Independent
Requires-Python: >=3.7
License-File: LICENSE
